[{"video_id": "m-z-0194c270-bbfb-7dd2-aaec-62d909b97b32", "scene_start": 0.0, "Scene_end": 1.0, "image": ["https://storage.videodb.io/media/u-0e58db00-6548-4d3c-b8c1-4ddddc072787/m-z-0194c270-bbfb-7dd2-aaec-62d909b97b32/frames/frm-scn-tt1sff1-0.0-1.0-0.5/img-5d1e4cff-122e-4a18-b9e3-0e3a985b0a6f.png"], "ground_truth": "HOW TO READ A CASE* And Understand What it Means \"What is reading but silent conversation?\" - Walter Savage Landor *Based in part on article by Julie Novkov at University at Albany, SUNY", "ocr": "# HOW TO READ A CASE* ## And Understand What it Means \"What is reading but silent conversation?\" - Walter Savage Landor [^0] [^0]: * Based in part on article by Julie Novkov at University at Albany, SUNY", "cer": 0.0913978494623656, "wer": 0.18181818181818182, "accuracy": 90.86021505376344, "order_agnostic_accuray": 100.0, "processing_time": 0.8285472393035889}, {"video_id": "m-z-0194c270-bbfb-7dd2-aaec-62d909b97b32", "scene_start": 1.0, "Scene_end": 2.0, "image": ["https://storage.videodb.io/media/u-0e58db00-6548-4d3c-b8c1-4ddddc072787/m-z-0194c270-bbfb-7dd2-aaec-62d909b97b32/frames/frm-scn-tt1sff1-1.0-2.0-1.5/img-d67343b8-ffd0-4ded-9cb5-8bd398b0ef5c.png"], "ground_truth": "HOW TO READ A CASE* And Understand What it Means \"What is reading but silent conversation?\" - Walter Savage Landor *Based in part on article by Julie Novkov at University at Albany, SUNY", "ocr": "# HOW TO READ A CASE* ## And Understand What it Means \"What is reading but silent conversation?\" - Walter Savage Landor [^0] [^0]: * Based in part on article by Julie Novkov at University at Albany, SUNY", "cer": 0.0913978494623656, "wer": 0.18181818181818182, "accuracy": 90.86021505376344, "order_agnostic_accuray": 100.0, "processing_time": 0.7339074611663818}, {"video_id": "m-z-0194c270-bbfb-7dd2-aaec-62d909b97b32", "scene_start": 2.0, "Scene_end": 3.0, "image": ["https://storage.videodb.io/media/u-0e58db00-6548-4d3c-b8c1-4ddddc072787/m-z-0194c270-bbfb-7dd2-aaec-62d909b97b32/frames/frm-scn-tt1sff1-2.0-3.0-2.5/img-b438e8fc-e8cb-4eb0-a3d3-7f97c295e68f.png"], "ground_truth": "HOW TO READ A CASE* And Understand What it Means \"What is reading but silent conversation?\" - Walter Savage Landor *Based in part on article by Julie Novkov at University at Albany, SUNY", "ocr": "# HOW TO READ A CASE* ## And Understand What it Means \"What is reading but silent conversation?\" - Walter Savage Landor [^0] [^0]: * Based in part on article by Julie Novkov at University at Albany, SUNY", "cer": 0.0913978494623656, "wer": 0.18181818181818182, "accuracy": 90.86021505376344, "order_agnostic_accuray": 100.0, "processing_time": 0.5724878311157227}, {"video_id": "m-z-0194c270-bbfb-7dd2-aaec-62d909b97b32", "scene_start": 3.0, "Scene_end": 4.0, "image": ["https://storage.videodb.io/media/u-0e58db00-6548-4d3c-b8c1-4ddddc072787/m-z-0194c270-bbfb-7dd2-aaec-62d909b97b32/frames/frm-scn-tt1sff1-3.0-4.0-3.5/img-6f09a960-1078-4fb6-8b50-3edc6391aa56.png"], "ground_truth": "HOW TO READ A CASE* And Understand What it Means \"What is reading but silent conversation?\" - Walter Savage Landor *Based in part on article by Julie Novkov at University at Albany, SUNY", "ocr": "# HOW TO READ A CASE* ## And Understand What it Means \"What is reading but silent conversation?\" - Walter Savage Landor [^0] [^0]: * Based in part on article by Julie Novkov at University at Albany, SUNY", "cer": 0.0913978494623656, "wer": 0.18181818181818182, "accuracy": 90.86021505376344, "order_agnostic_accuray": 100.0, "processing_time": 0.5840308666229248}, {"video_id": "m-z-0194c270-bbfb-7dd2-aaec-62d909b97b32", "scene_start": 4.0, "Scene_end": 5.0, "image": ["https://storage.videodb.io/media/u-0e58db00-6548-4d3c-b8c1-4ddddc072787/m-z-0194c270-bbfb-7dd2-aaec-62d909b97b32/frames/frm-scn-tt1sff1-4.0-5.0-4.5/img-4913d7dc-60e5-4c8e-91a7-d382f5f37755.png"], "ground_truth": "HOW TO READ A CASE* And Understand What it Means \"What is reading but silent conversation?\" - Walter Savage Landor *Based in part on article by Julie Novkov at University at Albany, SUNY", "ocr": "# HOW TO READ A CASE* ## And Understand What it Means \"What is reading but silent conversation?\" - Walter Savage Landor [^0] [^0]: * Based in part on article by Julie Novkov at University at Albany, SUNY", "cer": 0.0913978494623656, "wer": 0.18181818181818182, "accuracy": 90.86021505376344, "order_agnostic_accuray": 100.0, "processing_time": 0.6071572303771973}, {"video_id": "m-z-0194c270-bbfb-7dd2-aaec-62d909b97b32", "scene_start": 5.0, "Scene_end": 6.0, "image": ["https://storage.videodb.io/media/u-0e58db00-6548-4d3c-b8c1-4ddddc072787/m-z-0194c270-bbfb-7dd2-aaec-62d909b97b32/frames/frm-scn-tt1sff1-5.0-6.0-5.5/img-4da79b46-8ca2-49ff-926e-8a185f2f56fb.png"], "ground_truth": "HOW TO READ A CASE* And Understand What it Means \"What is reading but silent conversation?\" - Walter Savage Landor *Based in part on article by Julie Novkov at University at Albany, SUNY", "ocr": "# HOW TO READ A CASE* ## And Understand What it Means \"What is reading but silent conversation?\" - Walter Savage Landor [^0] [^0]: * Based in part on article by Julie Novkov at University at Albany, SUNY", "cer": 0.0913978494623656, "wer": 0.18181818181818182, "accuracy": 90.86021505376344, "order_agnostic_accuray": 100.0, "processing_time": 0.6506383419036865}, {"video_id": "m-z-0194c270-bbfb-7dd2-aaec-62d909b97b32", "scene_start": 6.0, "Scene_end": 7.0, "image": ["https://storage.videodb.io/media/u-0e58db00-6548-4d3c-b8c1-4ddddc072787/m-z-0194c270-bbfb-7dd2-aaec-62d909b97b32/frames/frm-scn-tt1sff1-6.0-7.0-6.5/img-ef714e74-c935-4d22-b159-1acf18a1c210.png"], "ground_truth": "HOW TO READ A CASE* And Understand What it Means \"What is reading but silent conversation?\" - Walter Savage Landor *Based in part on article by Julie Novkov at University at Albany, SUNY", "ocr": "# HOW TO READ A CASE* ## And Understand What it Means \"What is reading but silent conversation?\" - Walter Savage Landor [^0] [^0]: * Based in part on article by Julie Novkov at University at Albany, SUNY", "cer": 0.0913978494623656, "wer": 0.18181818181818182, "accuracy": 90.86021505376344, "order_agnostic_accuray": 100.0, "processing_time": 0.5657937526702881}, {"video_id": "m-z-0194c270-bbfb-7dd2-aaec-62d909b97b32", "scene_start": 7.0, "Scene_end": 8.0, "image": ["https://storage.videodb.io/media/u-0e58db00-6548-4d3c-b8c1-4ddddc072787/m-z-0194c270-bbfb-7dd2-aaec-62d909b97b32/frames/frm-scn-tt1sff1-7.0-8.0-7.5/img-6d2a65b0-5f06-46a0-aa03-f58ff6bce2fd.png"], "ground_truth": "HOW TO READ A CASE* And Understand What it Means \"What is reading but silent conversation?\" - Walter Savage Landor *Based in part on article by Julie Novkov at University at Albany, SUNY", "ocr": "# HOW TO READ A CASE* ## And Understand What it Means \"What is reading but silent conversation?\" - Walter Savage Landor [^0] [^0]: * Based in part on article by Julie Novkov at University at Albany, SUNY", "cer": 0.0913978494623656, "wer": 0.18181818181818182, "accuracy": 90.86021505376344, "order_agnostic_accuray": 100.0, "processing_time": 0.5243568420410156}, {"video_id": "m-z-0194c270-bbfb-7dd2-aaec-62d909b97b32", "scene_start": 8.0, "Scene_end": 9.0, "image": ["https://storage.videodb.io/media/u-0e58db00-6548-4d3c-b8c1-4ddddc072787/m-z-0194c270-bbfb-7dd2-aaec-62d909b97b32/frames/frm-scn-tt1sff1-8.0-9.0-8.5/img-5f760ae1-0b0b-4a45-b375-b1ab9f5cf58f.png"], "ground_truth": "HOW TO READ A CASE* And Understand What it Means \"What is reading but silent conversation?\" - Walter Savage Landor *Based in part on article by Julie Novkov at University at Albany, SUNY", "ocr": "# 1. WHAT IS THE BACKGROUND? ## - Citation - Where? - Is it a federal or state case? If it's a federal case, in what circuit was it decided? - Level of court? When? City of Austin v. Davis Tex.App. 3 Dist., 1985. Court of Appeals of Texas.Austin. CITY OF AUSTIN, Appellant, v. Kenneth Richard DAVIS, III, b/n/f Kenneth Richard Davis, Sr., et al., Appellees. No. 14246. June 5, 1985. Rehearing Denied June 26, 1985. Father disclaimed interest in action for wrongful death of his son and brought action against city hospital for his own mental distress and physical injuries sustained as bystander to finding of his son's body at base of airshaft.", "cer": 2.8763440860215055, "wer": 3.3333333333333335, "accuracy": -187.63440860215056, "order_agnostic_accuray": 95.16129032258065, "processing_time": 0.9041569232940674}, {"video_id": "m-z-0194c270-bbfb-7dd2-aaec-62d909b97b32", "scene_start": 9.0, "Scene_end": 10.0, "image": ["https://storage.videodb.io/media/u-0e58db00-6548-4d3c-b8c1-4ddddc072787/m-z-0194c270-bbfb-7dd2-aaec-62d909b97b32/frames/frm-scn-tt1sff1-9.0-10.0-9.5/img-eb203012-5a73-47f5-9c4f-dd0b7ee6688d.png"], "ground_truth": "1. WHAT IS THE BACKGROUND? - Citation Where? Is it a federal or state case? If it's a federal case, in what circuit was it decided? Level of court? When? City of Austin v. Davis Tex.App. 3 Dist.,1985. Court of Appeals of Texas.Austin. CITY OF AUSTIN, Appellant, v. Kenneth Richard DAVIS, III, b/n/f Kenneth Richard Davis, Sr., et al., Appellees. No. 14246. June 5, 1985. Rehearing Denied June 26, 1985. Father disclaimed interest in action for wrongful death of his son and brought action against city hospital for his own mental distress and physical injuries sustained as bystander to finding of his son's body at base of airshaft.", "ocr": "# 1. WHAT IS THE BACKGROUND? ## - Citation - Where? - Is it a federal or state case? If it's a federal case, in what circuit was it decided? - Level of court? When? City of Austin v. Davis Tex.App. 3 Dist., 1985. Court of Appeals of Texas.Austin. CITY OF AUSTIN, Appellant, v. Kenneth Richard DAVIS, III, b/n/f Kenneth Richard Davis, Sr., et al., Appellees. No. 14246. June 5, 1985. Rehearing Denied June 26, 1985. Father disclaimed interest in action for wrongful death of his son and brought action against city hospital for his own mental distress and physical injuries sustained as bystander to finding of his son's body at base of airshaft.", "cer": 0.018957345971563982, "wer": 0.06481481481481481, "accuracy": 98.10426540284361, "order_agnostic_accuray": 100.0, "processing_time": 0.6236495971679688}, {"video_id": "m-z-0194c270-bbfb-7dd2-aaec-62d909b97b32", "scene_start": 10.0, "Scene_end": 11.0, "image": ["https://storage.videodb.io/media/u-0e58db00-6548-4d3c-b8c1-4ddddc072787/m-z-0194c270-bbfb-7dd2-aaec-62d909b97b32/frames/frm-scn-tt1sff1-10.0-11.0-10.5/img-5acc1e65-c5c2-4c8a-beea-f9697846f31f.png"], "ground_truth": "1. WHAT IS THE BACKGROUND? - Citation Where? Is it a federal or state case? If it's a federal case, in what circuit was it decided? Level of court? When? City of Austin v. Davis Tex.App. 3 Dist.,1985. Court of Appeals of Texas.Austin. CITY OF AUSTIN, Appellant, v. Kenneth Richard DAVIS, III, b/n/f Kenneth Richard Davis, Sr., et al., Appellees. No. 14246. June 5, 1985. Rehearing Denied June 26, 1985. Father disclaimed interest in action for wrongful death of his son and brought action against city hospital for his own mental distress and physical injuries sustained as bystander to finding of his son's body at base of airshaft.", "ocr": "# 1. WHAT IS THE BACKGROUND? ## - Citation - Where? - Is it a federal or state case? If it's a federal case, in what circuit was it decided? - Level of court? ## - When? City of Austin v. Davis Tex.App. 3 Dist., 1985. Court of Appeals of Texas.Austin. CITY OF AUSTIN, Appellant, v. Kenneth Richard DAVIS, III, b/n/f Kenneth Richard Davis, Sr., et al., Appellees. No. 14246. June 5, 1985. Rehearing Denied June 26, 1985. Father disclaimed interest in action for wrongful death of his son and brought action against city hospital for his own mental distress and physical injuries sustained as bystander to finding of his son's body at base of airshaft.", "cer": 0.026856240126382307, "wer": 0.08333333333333333, "accuracy": 97.31437598736177, "order_agnostic_accuray": 100.0, "processing_time": 0.5546531677246094}, {"video_id": "m-z-0194c270-bbfb-7dd2-aaec-62d909b97b32", "scene_start": 11.0, "Scene_end": 12.0, "image": ["https://storage.videodb.io/media/u-0e58db00-6548-4d3c-b8c1-4ddddc072787/m-z-0194c270-bbfb-7dd2-aaec-62d909b97b32/frames/frm-scn-tt1sff1-11.0-12.0-11.5/img-4c60b764-39eb-4e7c-aac3-e8e2f2497518.png"], "ground_truth": "1. WHAT IS THE BACKGROUND? - Citation Where? Is it a federal or state case? If it's a federal case, in what circuit was it decided? Level of court? When? City of Austin v. Davis Tex.App. 3 Dist.,1985. Court of Appeals of Texas.Austin. CITY OF AUSTIN, Appellant, v. Kenneth Richard DAVIS, III, b/n/f Kenneth Richard Davis, Sr., et al., Appellees. No. 14246. June 5, 1985. Rehearing Denied June 26, 1985. Father disclaimed interest in action for wrongful death of his son and brought action against city hospital for his own mental distress and physical injuries sustained as bystander to finding of his son's body at base of airshaft.", "ocr": "# 1. WHAT IS THE BACKGROUND? ## - Citation - Where? - Is it a federal or state case? If it's a federal case, in what circuit was it decided? - Level of court? When? City of Austin v. Davis Tex.App. 3 Dist., 1985. Court of Appeals of Texas.Austin. CITY OF AUSTIN, Appellant, v. Kenneth Richard DAVIS, III, b/n/f Kenneth Richard Davis, Sr., et al., Appellees. No. 14246. June 5, 1985. Rehearing Denied June 26, 1985. Father disclaimed interest in action for wrongful death of his son and brought action against city hospital for his own mental distress and physical injuries sustained as bystander to finding of his son's body at base of airshaft.", "cer": 0.018957345971563982, "wer": 0.06481481481481481, "accuracy": 98.10426540284361, "order_agnostic_accuray": 100.0, "processing_time": 0.5774185657501221}, {"video_id": "m-z-0194c270-bbfb-7dd2-aaec-62d909b97b32", "scene_start": 12.0, "Scene_end": 13.0, "image": ["https://storage.videodb.io/media/u-0e58db00-6548-4d3c-b8c1-4ddddc072787/m-z-0194c270-bbfb-7dd2-aaec-62d909b97b32/frames/frm-scn-tt1sff1-12.0-13.0-12.5/img-d988a28b-d5c3-45bb-8725-cf780d05891f.png"], "ground_truth": "1. WHAT IS THE BACKGROUND? - Citation Where? Is it a federal or state case? If it's a federal case, in what circuit was it decided? Level of court? When? City of Austin v. Davis Tex.App. 3 Dist.,1985. Court of Appeals of Texas.Austin. CITY OF AUSTIN, Appellant, v. Kenneth Richard DAVIS, III, b/n/f Kenneth Richard Davis, Sr., et al., Appellees. No. 14246. June 5, 1985. Rehearing Denied June 26, 1985. Father disclaimed interest in action for wrongful death of his son and brought action against city hospital for his own mental distress and physical injuries sustained as bystander to finding of his son's body at base of airshaft.", "ocr": "# 1. WHAT IS THE BACKGROUND? ## - Citation - Where? - Is it a federal or state case? If it's a federal case, in what circuit was it decided? - Level of court? When? City of Austin v. Davis Tex.App. 3 Dist., 1985. Court of Appeals of Texas.Austin. CITY OF AUSTIN, Appellant, v. Kenneth Richard DAVIS, III, b/n/f Kenneth Richard Davis, Sr., et al., Appellees. No. 14246. June 5, 1985. Rehearing Denied June 26, 1985. Father disclaimed interest in action for wrongful death of his son and brought action against city hospital for his own mental distress and physical injuries sustained as bystander to finding of his son's body at base of airshaft.", "cer": 0.018957345971563982, "wer": 0.06481481481481481, "accuracy": 98.10426540284361, "order_agnostic_accuray": 100.0, "processing_time": 0.4803776741027832}, {"video_id": "m-z-0194c270-bbfb-7dd2-aaec-62d909b97b32", "scene_start": 13.0, "Scene_end": 14.0, "image": ["https://storage.videodb.io/media/u-0e58db00-6548-4d3c-b8c1-4ddddc072787/m-z-0194c270-bbfb-7dd2-aaec-62d909b97b32/frames/frm-scn-tt1sff1-13.0-14.0-13.5/img-a2c471cc-ffeb-44ef-ab37-04cafd3058db.png"], "ground_truth": "1. WHAT IS THE BACKGROUND? - Citation Where? Is it a federal or state case? If it's a federal case, in what circuit was it decided? Level of court? When? City of Austin v. Davis Tex.App. 3 Dist.,1985. Court of Appeals of Texas.Austin. CITY OF AUSTIN, Appellant, v. Kenneth Richard DAVIS, III, b/n/f Kenneth Richard Davis, Sr., et al., Appellees. No. 14246. June 5, 1985. Rehearing Denied June 26, 1985. Father disclaimed interest in action for wrongful death of his son and brought action against city hospital for his own mental distress and physical injuries sustained as bystander to finding of his son's body at base of airshaft.", "ocr": "# 1. WHAT IS THE BACKGROUND? ## - Citation - Where? - Is it a federal or state case? If it's a federal case, in what circuit was it decided? - Level of court? When? City of Austin v. Davis Tex.App. 3 Dist., 1985. Court of Appeals of Texas.Austin. CITY OF AUSTIN, Appellant, v. Kenneth Richard DAVIS, III, b/n/f Kenneth Richard Davis, Sr., et al., Appellees. No. 14246. June 5, 1985. Rehearing Denied June 26, 1985. Father disclaimed interest in action for wrongful death of his son and brought action against city hospital for his own mental distress and physical injuries sustained as bystander to finding of his son's body at base of airshaft.", "cer": 0.018957345971563982, "wer": 0.06481481481481481, "accuracy": 98.10426540284361, "order_agnostic_accuray": 100.0, "processing_time": 1.6450085639953613}, {"video_id": "m-z-0194c270-bbfb-7dd2-aaec-62d909b97b32", "scene_start": 14.0, "Scene_end": 15.0, "image": ["https://storage.videodb.io/media/u-0e58db00-6548-4d3c-b8c1-4ddddc072787/m-z-0194c270-bbfb-7dd2-aaec-62d909b97b32/frames/frm-scn-tt1sff1-14.0-15.0-14.5/img-9e6dc430-30fc-4834-baa2-a96801d0523e.png"], "ground_truth": "1. WHAT IS THE BACKGROUND? - Citation Where? Is it a federal or state case? If it's a federal case, in what circuit was it decided? Level of court? When? City of Austin v. Davis Tex.App. 3 Dist.,1985. Court of Appeals of Texas.Austin. CITY OF AUSTIN, Appellant, v. Kenneth Richard DAVIS, III, b/n/f Kenneth Richard Davis, Sr., et al., Appellees. No. 14246. June 5, 1985. Rehearing Denied June 26, 1985. Father disclaimed interest in action for wrongful death of his son and brought action against city hospital for his own mental distress and physical injuries sustained as bystander to finding of his son's body at base of airshaft.", "ocr": "# 1. WHAT IS THE BACKGROUND? ## - Citation - Where? - Is it a federal or state case? If it's a federal case, in what circuit was it decided? - Level of court? When? City of Austin v. Davis Tex.App. 3 Dist., 1985. Court of Appeals of Texas.Austin. CITY OF AUSTIN, Appellant, v. Kenneth Richard DAVIS, III, b/n/f Kenneth Richard Davis, Sr., et al., Appellees. No. 14246. June 5, 1985. Rehearing Denied June 26, 1985. Father disclaimed interest in action for wrongful death of his son and brought action against city hospital for his own mental distress and physical injuries sustained as bystander to finding of his son's body at base of airshaft.", "cer": 0.018957345971563982, "wer": 0.06481481481481481, "accuracy": 98.10426540284361, "order_agnostic_accuray": 100.0, "processing_time": 2.0918450355529785}, {"video_id": "m-z-0194c270-bbfb-7dd2-aaec-62d909b97b32", "scene_start": 15.0, "Scene_end": 16.0, "image": ["https://storage.videodb.io/media/u-0e58db00-6548-4d3c-b8c1-4ddddc072787/m-z-0194c270-bbfb-7dd2-aaec-62d909b97b32/frames/frm-scn-tt1sff1-15.0-16.0-15.5/img-9fed1a77-1643-46fd-acc6-a1a76a2e3d3b.png"], "ground_truth": "1. WHAT IS THE BACKGROUND? - Citation Where? Is it a federal or state case? If it's a federal case, in what circuit was it decided? Level of court? When? City of Austin v. Davis Tex.App. 3 Dist.,1985. Court of Appeals of Texas.Austin. CITY OF AUSTIN, Appellant, v. Kenneth Richard DAVIS, III, b/n/f Kenneth Richard Davis, Sr., et al., Appellees. No. 14246. June 5, 1985. Rehearing Denied June 26, 1985. Father disclaimed interest in action for wrongful death of his son and brought action against city hospital for his own mental distress and physical injuries sustained as bystander to finding of his son's body at base of airshaft.", "ocr": "# 1. WHAT IS THE BACKGROUND? ## - Citation - Where? - Is it a federal or state case? If it's a federal case, in what circuit was it decided? - Level of court? When? City of Austin v. Davis Tex.App. 3 Dist., 1985. Court of Appeals of Texas.Austin. CITY OF AUSTIN, Appellant, v. Kenneth Richard DAVIS, III, b/n/f Kenneth Richard Davis, Sr., et al., Appellees. No. 14246. June 5, 1985. Rehearing Denied June 26, 1985. Father disclaimed interest in action for wrongful death of his son and brought action against city hospital for his own mental distress and physical injuries sustained as bystander to finding of his son's body at base of airshaft.", "cer": 0.018957345971563982, "wer": 0.06481481481481481, "accuracy": 98.10426540284361, "order_agnostic_accuray": 100.0, "processing_time": 0.7688140869140625}, {"video_id": "m-z-0194c270-bbfb-7dd2-aaec-62d909b97b32", "scene_start": 16.0, "Scene_end": 17.0, "image": ["https://storage.videodb.io/media/u-0e58db00-6548-4d3c-b8c1-4ddddc072787/m-z-0194c270-bbfb-7dd2-aaec-62d909b97b32/frames/frm-scn-tt1sff1-16.0-17.0-16.5/img-a5ebe168-fe17-49bd-9065-82807be2130c.png"], "ground_truth": "1. WHAT IS THE BACKGROUND? - Citation Where? Is it a federal or state case? If it's a federal case, in what circuit was it decided? Level of court? When? City of Austin v. Davis Tex.App. 3 Dist.,1985. Court of Appeals of Texas.Austin. CITY OF AUSTIN, Appellant, v. Kenneth Richard DAVIS, III, b/n/f Kenneth Richard Davis, Sr., et al., Appellees. No. 14246. June 5, 1985. Rehearing Denied June 26, 1985. Father disclaimed interest in action for wrongful death of his son and brought action against city hospital for his own mental distress and physical injuries sustained as bystander to finding of his son's body at base of airshaft.", "ocr": "# 1. WHAT IS THE BACKGROUND? ## - Citation - Where? - Is it a federal or state case? If it's a federal case, in what circuit was it decided? - Level of court? When? City of Austin v. Davis Tex.App. 3 Dist., 1985. Court of Appeals of Texas.Austin. CITY OF AUSTIN, Appellant, v. Kenneth Richard DAVIS, III, b/n/f Kenneth Richard Davis, Sr., et al., Appellees. No. 14246. June 5, 1985. Rehearing Denied June 26, 1985. Father disclaimed interest in action for wrongful death of his son and brought action against city hospital for his own mental distress and physical injuries sustained as bystander to finding of his son's body at base of airshaft.", "cer": 0.018957345971563982, "wer": 0.06481481481481481, "accuracy": 98.10426540284361, "order_agnostic_accuray": 100.0, "processing_time": 2.0942587852478027}, {"video_id": "m-z-0194c270-bbfb-7dd2-aaec-62d909b97b32", "scene_start": 17.0, "Scene_end": 18.0, "image": ["https://storage.videodb.io/media/u-0e58db00-6548-4d3c-b8c1-4ddddc072787/m-z-0194c270-bbfb-7dd2-aaec-62d909b97b32/frames/frm-scn-tt1sff1-17.0-18.0-17.5/img-adf233b7-be10-45a5-82c8-65d655be0a75.png"], "ground_truth": "1. WHAT IS THE BACKGROUND? - Citation Where? Is it a federal or state case? If it's a federal case, in what circuit was it decided? Level of court? When? City of Austin v. Davis Tex.App. 3 Dist.,1985. Court of Appeals of Texas.Austin. CITY OF AUSTIN, Appellant, v. Kenneth Richard DAVIS, III, b/n/f Kenneth Richard Davis, Sr., et al., Appellees. No. 14246. June 5, 1985. Rehearing Denied June 26, 1985. Father disclaimed interest in action for wrongful death of his son and brought action against city hospital for his own mental distress and physical injuries sustained as bystander to finding of his son's body at base of airshaft.", "ocr": "# 1. WHAT IS THE BACKGROUND? ## - Citation - Where? - Is it a federal or state case? If it's a federal case, in what circuit was it decided? - Level of court? When? City of Austin v. Davis Tex.App. 3 Dist., 1985. Court of Appeals of Texas.Austin. CITY OF AUSTIN, Appellant, v. Kenneth Richard DAVIS, III, b/n/f Kenneth Richard Davis, Sr., et al., Appellees. No. 14246. June 5, 1985. Rehearing Denied June 26, 1985. Father disclaimed interest in action for wrongful death of his son and brought action against city hospital for his own mental distress and physical injuries sustained as bystander to finding of his son's body at base of airshaft.", "cer": 0.018957345971563982, "wer": 0.06481481481481481, "accuracy": 98.10426540284361, "order_agnostic_accuray": 100.0, "processing_time": 1.997602939605713}, {"video_id": "m-z-0194c270-bbfb-7dd2-aaec-62d909b97b32", "scene_start": 18.0, "Scene_end": 19.0, "image": ["https://storage.videodb.io/media/u-0e58db00-6548-4d3c-b8c1-4ddddc072787/m-z-0194c270-bbfb-7dd2-aaec-62d909b97b32/frames/frm-scn-tt1sff1-18.0-19.0-18.5/img-fbb4bbc6-a581-4db9-8e7c-ba3a2e4b6e0f.png"], "ground_truth": "1. WHAT IS THE BACKGROUND? - Citation Where? Is it a federal or state case? If it's a federal case, in what circuit was it decided? Level of court? When? City of Austin v. Davis Tex.App. 3 Dist.,1985. Court of Appeals of Texas.Austin. CITY OF AUSTIN, Appellant, v. Kenneth Richard DAVIS, III, b/n/f Kenneth Richard Davis, Sr., et al., Appellees. No. 14246. June 5, 1985. Rehearing Denied June 26, 1985. Father disclaimed interest in action for wrongful death of his son and brought action against city hospital for his own mental distress and physical injuries sustained as bystander to finding of his son's body at base of airshaft.", "ocr": "# 1. WHAT IS THE BACKGROUND? ## - Citation - Where? - Is it a federal or state case? If it's a federal case, in what circuit was it decided? - Level of court? When? City of Austin v. Davis Tex.App. 3 Dist., 1985. Court of Appeals of Texas.Austin. CITY OF AUSTIN, Appellant, v. Kenneth Richard DAVIS, III, b/n/f Kenneth Richard Davis, Sr., et al., Appellees. No. 14246. June 5, 1985. Rehearing Denied June 26, 1985. Father disclaimed interest in action for wrongful death of his son and brought action against city hospital for his own mental distress and physical injuries sustained as bystander to finding of his son's body at base of airshaft.", "cer": 0.018957345971563982, "wer": 0.06481481481481481, "accuracy": 98.10426540284361, "order_agnostic_accuray": 100.0, "processing_time": 1.835153579711914}, {"video_id": "m-z-0194c270-bbfb-7dd2-aaec-62d909b97b32", "scene_start": 19.0, "Scene_end": 20.0, "image": ["https://storage.videodb.io/media/u-0e58db00-6548-4d3c-b8c1-4ddddc072787/m-z-0194c270-bbfb-7dd2-aaec-62d909b97b32/frames/frm-scn-tt1sff1-19.0-20.0-19.5/img-407eea8f-f0a3-43c9-9100-84698fbf7a4b.png"], "ground_truth": "1. WHAT IS THE BACKGROUND? - Citation Where? Is it a federal or state case? If it's a federal case, in what circuit was it decided? Level of court? When? City of Austin v. Davis Tex.App. 3 Dist.,1985. Court of Appeals of Texas.Austin. CITY OF AUSTIN, Appellant, v. Kenneth Richard DAVIS, III, b/n/f Kenneth Richard Davis, Sr., et al., Appellees. No. 14246. June 5, 1985. Rehearing Denied June 26, 1985. Father disclaimed interest in action for wrongful death of his son and brought action against city hospital for his own mental distress and physical injuries sustained as bystander to finding of his son's body at base of airshaft.", "ocr": "# 1. WHAT IS THE BACKGROUND? ## - Citation - Where? - Is it a federal or state case? If it's a federal case, in what circuit was it decided? - Level of court? When? City of Austin v. Davis Tex.App. 3 Dist., 1985. Court of Appeals of Texas.Austin. CITY OF AUSTIN, Appellant, v. Kenneth Richard DAVIS, III, b/n/f Kenneth Richard Davis, Sr., et al., Appellees. No. 14246. June 5, 1985. Rehearing Denied June 26, 1985. Father disclaimed interest in action for wrongful death of his son and brought action against city hospital for his own mental distress and physical injuries sustained as bystander to finding of his son's body at base of airshaft.", "cer": 0.018957345971563982, "wer": 0.06481481481481481, "accuracy": 98.10426540284361, "order_agnostic_accuray": 100.0, "processing_time": 1.7610695362091064}, {"video_id": "m-z-0194c270-bbfb-7dd2-aaec-62d909b97b32", "scene_start": 20.0, "Scene_end": 21.0, "image": ["https://storage.videodb.io/media/u-0e58db00-6548-4d3c-b8c1-4ddddc072787/m-z-0194c270-bbfb-7dd2-aaec-62d909b97b32/frames/frm-scn-tt1sff1-20.0-21.0-20.5/img-19d8dfd3-bbda-43d0-87a5-f6d4b1677d02.png"], "ground_truth": "1. WHAT IS THE BACKGROUND? - Citation Where? Is it a federal or state case? If it's a federal case, in what circuit was it decided? Level of court? When? City of Austin v. Davis Tex.App. 3 Dist.,1985. Court of Appeals of Texas.Austin. CITY OF AUSTIN, Appellant, v. Kenneth Richard DAVIS, III, b/n/f Kenneth Richard Davis, Sr., et al., Appellees. No. 14246. June 5, 1985. Rehearing Denied June 26, 1985. Father disclaimed interest in action for wrongful death of his son and brought action against city hospital for his own mental distress and physical injuries sustained as bystander to finding of his son's body at base of airshaft.", "ocr": "# 1. WHAT IS THE BACKGROUND? ## - Citation - Where? - Is it a federal or state case? If it's a federal case, in what circuit was it decided? - Level of court? When? City of Austin v. Davis Tex.App. 3 Dist., 1985. Court of Appeals of Texas.Austin. CITY OF AUSTIN, Appellant, v. Kenneth Richard DAVIS, III, b/n/f Kenneth Richard Davis, Sr., et al., Appellees. No. 14246. June 5, 1985. Rehearing Denied June 26, 1985. Father disclaimed interest in action for wrongful death of his son and brought action against city hospital for his own mental distress and physical injuries sustained as bystander to finding of his son's body at base of airshaft.", "cer": 0.018957345971563982, "wer": 0.06481481481481481, "accuracy": 98.10426540284361, "order_agnostic_accuray": 100.0, "processing_time": 1.910426139831543}, {"video_id": "m-z-0194c270-bbfb-7dd2-aaec-62d909b97b32", "scene_start": 21.0, "Scene_end": 22.0, "image": ["https://storage.videodb.io/media/u-0e58db00-6548-4d3c-b8c1-4ddddc072787/m-z-0194c270-bbfb-7dd2-aaec-62d909b97b32/frames/frm-scn-tt1sff1-21.0-22.0-21.5/img-d84bcf54-07d1-44c8-abef-f6034e6f2e6c.png"], "ground_truth": "1. WHAT IS THE BACKGROUND? - Citation Where? Is it a federal or state case? If it's a federal case, in what circuit was it decided? Level of court? When? City of Austin v. Davis Tex.App. 3 Dist.,1985. Court of Appeals of Texas.Austin. CITY OF AUSTIN, Appellant, v. Kenneth Richard DAVIS, III, b/n/f Kenneth Richard Davis, Sr., et al., Appellees. No. 14246. June 5, 1985. Rehearing Denied June 26, 1985. Father disclaimed interest in action for wrongful death of his son and brought action against city hospital for his own mental distress and physical injuries sustained as bystander to finding of his son's body at base of airshaft.", "ocr": "# 1. WHAT IS THE BACKGROUND? ## - Citation - Where? - Is it a federal or state case? If it's a federal case, in what circuit was it decided? - Level of court? When? City of Austin v. Davis Tex.App. 3 Dist., 1985. Court of Appeals of Texas.Austin. CITY OF AUSTIN, Appellant, v. Kenneth Richard DAVIS, III, b/n/f Kenneth Richard Davis, Sr., et al., Appellees. No. 14246. June 5, 1985. Rehearing Denied June 26, 1985. Father disclaimed interest in action for wrongful death of his son and brought action against city hospital for his own mental distress and physical injuries sustained as bystander to finding of his son's body at base of airshaft.", "cer": 0.018957345971563982, "wer": 0.06481481481481481, "accuracy": 98.10426540284361, "order_agnostic_accuray": 100.0, "processing_time": 0.853931188583374}, {"video_id": "m-z-0194c270-bbfb-7dd2-aaec-62d909b97b32", "scene_start": 22.0, "Scene_end": 23.0, "image": ["https://storage.videodb.io/media/u-0e58db00-6548-4d3c-b8c1-4ddddc072787/m-z-0194c270-bbfb-7dd2-aaec-62d909b97b32/frames/frm-scn-tt1sff1-22.0-23.0-22.5/img-7508c1cc-0483-4621-af32-d9f84316bdcc.png"], "ground_truth": "1. WHAT IS THE BACKGROUND? - Citation Where? Is it a federal or state case? If it's a federal case, in what circuit was it decided? Level of court? When? City of Austin v. Davis Tex.App. 3 Dist.,1985. Court of Appeals of Texas.Austin. CITY OF AUSTIN, Appellant, v. Kenneth Richard DAVIS, III, b/n/f Kenneth Richard Davis, Sr., et al., Appellees. No. 14246. June 5, 1985. Rehearing Denied June 26, 1985. Father disclaimed interest in action for wrongful death of his son and brought action against city hospital for his own mental distress and physical injuries sustained as bystander to finding of his son's body at base of airshaft.", "ocr": "# 1. WHAT IS THE BACKGROUND? ## - Citation - Where? - Is it a federal or state case? If it's a federal case, in what circuit was it decided? - Level of court? When? City of Austin v. Davis Tex.App. 3 Dist., 1985. Court of Appeals of Texas.Austin. CITY OF AUSTIN, Appellant, v. Kenneth Richard DAVIS, III, b/n/f Kenneth Richard Davis, Sr., et al., Appellees. No. 14246. June 5, 1985. Rehearing Denied June 26, 1985. Father disclaimed interest in action for wrongful death of his son and brought action against city hospital for his own mental distress and physical injuries sustained as bystander to finding of his son's body at base of airshaft.", "cer": 0.018957345971563982, "wer": 0.06481481481481481, "accuracy": 98.10426540284361, "order_agnostic_accuray": 100.0, "processing_time": 1.7187364101409912}, {"video_id": "m-z-0194c270-bbfb-7dd2-aaec-62d909b97b32", "scene_start": 23.0, "Scene_end": 24.0, "image": ["https://storage.videodb.io/media/u-0e58db00-6548-4d3c-b8c1-4ddddc072787/m-z-0194c270-bbfb-7dd2-aaec-62d909b97b32/frames/frm-scn-tt1sff1-23.0-24.0-23.5/img-5c715892-0538-4dcd-a3f6-59d0041200dd.png"], "ground_truth": "1. WHAT IS THE BACKGROUND? - Citation Where? Is it a federal or state case? If it's a federal case, in what circuit was it decided? Level of court? When? City of Austin v. Davis Tex.App. 3 Dist.,1985. Court of Appeals of Texas.Austin. CITY OF AUSTIN, Appellant, v. Kenneth Richard DAVIS, III, b/n/f Kenneth Richard Davis, Sr., et al., Appellees. No. 14246. June 5, 1985. Rehearing Denied June 26, 1985. Father disclaimed interest in action for wrongful death of his son and brought action against city hospital for his own mental distress and physical injuries sustained as bystander to finding of his son's body at base of airshaft.", "ocr": "# 1. WHAT IS THE BACKGROUND? ## - Citation - Where? - Is it a federal or state case? If it's a federal case, in what circuit was it decided? - Level of court? When? City of Austin v. Davis Tex.App. 3 Dist., 1985. Court of Appeals of Texas.Austin. CITY OF AUSTIN, Appellant, v. Kenneth Richard DAVIS, III, b/n/f Kenneth Richard Davis, Sr., et al., Appellees. No. 14246. June 5, 1985. Rehearing Denied June 26, 1985. Father disclaimed interest in action for wrongful death of his son and brought action against city hospital for his own mental distress and physical injuries sustained as bystander to finding of his son's body at base of airshaft.", "cer": 0.018957345971563982, "wer": 0.06481481481481481, "accuracy": 98.10426540284361, "order_agnostic_accuray": 100.0, "processing_time": 1.9845454692840576}, {"video_id": "m-z-0194c270-bbfb-7dd2-aaec-62d909b97b32", "scene_start": 24.0, "Scene_end": 25.0, "image": ["https://storage.videodb.io/media/u-0e58db00-6548-4d3c-b8c1-4ddddc072787/m-z-0194c270-bbfb-7dd2-aaec-62d909b97b32/frames/frm-scn-tt1sff1-24.0-25.0-24.5/img-8d506089-06b5-49d3-8173-eb463910c3a4.png"], "ground_truth": "1. WHAT IS THE BACKGROUND? - Citation Where? Is it a federal or state case? If it's a federal case, in what circuit was it decided? Level of court? When? City of Austin v. Davis Tex.App. 3 Dist.,1985. Court of Appeals of Texas.Austin. CITY OF AUSTIN, Appellant, v. Kenneth Richard DAVIS, III, b/n/f Kenneth Richard Davis, Sr., et al., Appellees. No. 14246. June 5, 1985. Rehearing Denied June 26, 1985. Father disclaimed interest in action for wrongful death of his son and brought action against city hospital for his own mental distress and physical injuries sustained as bystander to finding of his son's body at base of airshaft.", "ocr": "# 1. WHAT IS THE BACKGROUND? ## - Citation - Where? - Is it a federal or state case? If it's a federal case, in what circuit was it decided? - Level of court? When? City of Austin v. Davis Tex.App. 3 Dist., 1985. Court of Appeals of Texas.Austin. CITY OF AUSTIN, Appellant, v. Kenneth Richard DAVIS, III, b/n/f Kenneth Richard Davis, Sr., et al., Appellees. No. 14246. June 5, 1985. Rehearing Denied June 26, 1985. Father disclaimed interest in action for wrongful death of his son and brought action against city hospital for his own mental distress and physical injuries sustained as bystander to finding of his son's body at base of airshaft.", "cer": 0.018957345971563982, "wer": 0.06481481481481481, "accuracy": 98.10426540284361, "order_agnostic_accuray": 100.0, "processing_time": 1.7627155780792236}, {"video_id": "m-z-0194c270-bbfb-7dd2-aaec-62d909b97b32", "scene_start": 25.0, "Scene_end": 26.0, "image": ["https://storage.videodb.io/media/u-0e58db00-6548-4d3c-b8c1-4ddddc072787/m-z-0194c270-bbfb-7dd2-aaec-62d909b97b32/frames/frm-scn-tt1sff1-25.0-26.0-25.5/img-1213283a-93ac-497d-992c-96b801d4355b.png"], "ground_truth": "1. WHAT IS THE BACKGROUND? - Citation Where? Is it a federal or state case? If it's a federal case, in what circuit was it decided? Level of court? When? City of Austin v. Davis Tex.App. 3 Dist.,1985. Court of Appeals of Texas.Austin. CITY OF AUSTIN, Appellant, v. Kenneth Richard DAVIS, III, b/n/f Kenneth Richard Davis, Sr., et al., Appellees. No. 14246. June 5, 1985. Rehearing Denied June 26, 1985. Father disclaimed interest in action for wrongful death of his son and brought action against city hospital for his own mental distress and physical injuries sustained as bystander to finding of his son's body at base of airshaft.", "ocr": "# 1. WHAT IS THE BACKGROUND? ## - Citation - Where? - Is it a federal or state case? If it's a federal case, in what circuit was it decided? - Level of court? When? City of Austin v. Davis Tex.App. 3 Dist., 1985. Court of Appeals of Texas.Austin. CITY OF AUSTIN, Appellant, v. Kenneth Richard DAVIS, III, b/n/f Kenneth Richard Davis, Sr., et al., Appellees. No. 14246. June 5, 1985. Rehearing Denied June 26, 1985. Father disclaimed interest in action for wrongful death of his son and brought action against city hospital for his own mental distress and physical injuries sustained as bystander to finding of his son's body at base of airshaft.", "cer": 0.018957345971563982, "wer": 0.06481481481481481, "accuracy": 98.10426540284361, "order_agnostic_accuray": 100.0, "processing_time": 1.7215156555175781}, {"video_id": "m-z-0194c270-bbfb-7dd2-aaec-62d909b97b32", "scene_start": 26.0, "Scene_end": 27.0, "image": ["https://storage.videodb.io/media/u-0e58db00-6548-4d3c-b8c1-4ddddc072787/m-z-0194c270-bbfb-7dd2-aaec-62d909b97b32/frames/frm-scn-tt1sff1-26.0-27.0-26.5/img-e05b7ee4-65d3-478f-be4c-0dae668dab5e.png"], "ground_truth": "1. WHAT IS THE BACKGROUND? - Citation Where? Is it a federal or state case? If it's a federal case, in what circuit was it decided? Level of court? When? City of Austin v. Davis Tex.App. 3 Dist.,1985. Court of Appeals of Texas.Austin. CITY OF AUSTIN, Appellant, v. Kenneth Richard DAVIS, III, b/n/f Kenneth Richard Davis, Sr., et al., Appellees. No. 14246. June 5, 1985. Rehearing Denied June 26, 1985. Father disclaimed interest in action for wrongful death of his son and brought action against city hospital for his own mental distress and physical injuries sustained as bystander to finding of his son's body at base of airshaft.", "ocr": "# 1. WHAT IS THE BACKGROUND? ## - Citation - Where? - Is it a federal or state case? If it's a federal case, in what circuit was it decided? - Level of court? When? City of Austin v. Davis Tex.App. 3 Dist., 1985. Court of Appeals of Texas.Austin. CITY OF AUSTIN, Appellant, v. Kenneth Richard DAVIS, III, b/n/f Kenneth Richard Davis, Sr., et al., Appellees. No. 14246. June 5, 1985. Rehearing Denied June 26, 1985. Father disclaimed interest in action for wrongful death of his son and brought action against city hospital for his own mental distress and physical injuries sustained as bystander to finding of his son's body at base of airshaft.", "cer": 0.018957345971563982, "wer": 0.06481481481481481, "accuracy": 98.10426540284361, "order_agnostic_accuray": 100.0, "processing_time": 2.0009632110595703}, {"video_id": "m-z-0194c270-bbfb-7dd2-aaec-62d909b97b32", "scene_start": 27.0, "Scene_end": 28.0, "image": ["https://storage.videodb.io/media/u-0e58db00-6548-4d3c-b8c1-4ddddc072787/m-z-0194c270-bbfb-7dd2-aaec-62d909b97b32/frames/frm-scn-tt1sff1-27.0-28.0-27.5/img-1051d865-cfd7-4e22-8af3-bffd6d760c93.png"], "ground_truth": "1. WHAT IS THE BACKGROUND? - Citation Where? Is it a federal or state case? If it's a federal case, in what circuit was it decided? Level of court? When? City of Austin v. Davis Tex.App. 3 Dist.,1985. Court of Appeals of Texas.Austin. CITY OF AUSTIN, Appellant, v. Kenneth Richard DAVIS, III, b/n/f Kenneth Richard Davis, Sr., et al., Appellees. No. 14246. June 5, 1985. Rehearing Denied June 26, 1985. Father disclaimed interest in action for wrongful death of his son and brought action against city hospital for his own mental distress and physical injuries sustained as bystander to finding of his son's body at base of airshaft.", "ocr": "# 1. WHAT IS THE BACKGROUND? ## - Citation - Where? - Is it a federal or state case? If it's a federal case, in what circuit was it decided? - Level of court? When? City of Austin v. Davis Tex.App. 3 Dist., 1985. Court of Appeals of Texas.Austin. CITY OF AUSTIN, Appellant, v. Kenneth Richard DAVIS, III, b/n/f Kenneth Richard Davis, Sr., et al., Appellees. No. 14246. June 5, 1985. Rehearing Denied June 26, 1985. Father disclaimed interest in action for wrongful death of his son and brought action against city hospital for his own mental distress and physical injuries sustained as bystander to finding of his son's body at base of airshaft.", "cer": 0.018957345971563982, "wer": 0.06481481481481481, "accuracy": 98.10426540284361, "order_agnostic_accuray": 100.0, "processing_time": 1.6858046054840088}, {"video_id": "m-z-0194c270-bbfb-7dd2-aaec-62d909b97b32", "scene_start": 28.0, "Scene_end": 29.0, "image": ["https://storage.videodb.io/media/u-0e58db00-6548-4d3c-b8c1-4ddddc072787/m-z-0194c270-bbfb-7dd2-aaec-62d909b97b32/frames/frm-scn-tt1sff1-28.0-29.0-28.5/img-3c57658c-62ec-43de-8939-2ae187803403.png"], "ground_truth": "1. WHAT IS THE BACKGROUND? - Citation Where? Is it a federal or state case? If it's a federal case, in what circuit was it decided? Level of court? When? City of Austin v. Davis Tex.App. 3 Dist.,1985. Court of Appeals of Texas.Austin. CITY OF AUSTIN, Appellant, v. Kenneth Richard DAVIS, III, b/n/f Kenneth Richard Davis, Sr., et al., Appellees. No. 14246. June 5, 1985. Rehearing Denied June 26, 1985. Father disclaimed interest in action for wrongful death of his son and brought action against city hospital for his own mental distress and physical injuries sustained as bystander to finding of his son's body at base of airshaft.", "ocr": "# 1. WHAT IS THE BACKGROUND? ## - Citation - Where? - Is it a federal or state case? If it's a federal case, in what circuit was it decided? - Level of court? When? City of Austin v. Davis Tex.App. 3 Dist., 1985. Court of Appeals of Texas.Austin. CITY OF AUSTIN, Appellant, v. Kenneth Richard DAVIS, III, b/n/f Kenneth Richard Davis, Sr., et al., Appellees. No. 14246. June 5, 1985. Rehearing Denied June 26, 1985. Father disclaimed interest in action for wrongful death of his son and brought action against city hospital for his own mental distress and physical injuries sustained as bystander to finding of his son's body at base of airshaft.", "cer": 0.018957345971563982, "wer": 0.06481481481481481, "accuracy": 98.10426540284361, "order_agnostic_accuray": 100.0, "processing_time": 2.1179158687591553}, {"video_id": "m-z-0194c270-bbfb-7dd2-aaec-62d909b97b32", "scene_start": 29.0, "Scene_end": 30.0, "image": ["https://storage.videodb.io/media/u-0e58db00-6548-4d3c-b8c1-4ddddc072787/m-z-0194c270-bbfb-7dd2-aaec-62d909b97b32/frames/frm-scn-tt1sff1-29.0-30.0-29.5/img-9efd3a52-c942-4643-aa4d-1c3ecabbfd65.png"], "ground_truth": "1. WHAT IS THE BACKGROUND? - Citation Where? Is it a federal or state case? If it's a federal case, in what circuit was it decided? Level of court? When? City of Austin v. Davis Tex.App. 3 Dist.,1985. Court of Appeals of Texas.Austin. CITY OF AUSTIN, Appellant, v. Kenneth Richard DAVIS, III, b/n/f Kenneth Richard Davis, Sr., et al., Appellees. No. 14246. June 5, 1985. Rehearing Denied June 26, 1985. Father disclaimed interest in action for wrongful death of his son and brought action against city hospital for his own mental distress and physical injuries sustained as bystander to finding of his son's body at base of airshaft.", "ocr": "# 1. WHAT IS THE BACKGROUND? ## - Citation - Where? - Is it a federal or state case? If it's a federal case, in what circuit was it decided? - Level of court? When? City of Austin v. Davis Tex.App. 3 Dist., 1985. Court of Appeals of Texas.Austin. CITY OF AUSTIN, Appellant, v. Kenneth Richard DAVIS, III, b/n/f Kenneth Richard Davis, Sr., et al., Appellees. No. 14246. June 5, 1985. Rehearing Denied June 26, 1985. Father disclaimed interest in action for wrongful death of his son and brought action against city hospital for his own mental distress and physical injuries sustained as bystander to finding of his son's body at base of airshaft.", "cer": 0.018957345971563982, "wer": 0.06481481481481481, "accuracy": 98.10426540284361, "order_agnostic_accuray": 100.0, "processing_time": 1.6634550094604492}, {"video_id": "m-z-0194c270-bbfb-7dd2-aaec-62d909b97b32", "scene_start": 30.0, "Scene_end": 31.0, "image": ["https://storage.videodb.io/media/u-0e58db00-6548-4d3c-b8c1-4ddddc072787/m-z-0194c270-bbfb-7dd2-aaec-62d909b97b32/frames/frm-scn-tt1sff1-30.0-31.0-30.5/img-54100263-8e39-4c6c-8c47-5612a78472f1.png"], "ground_truth": "1. WHAT IS THE BACKGROUND? - Citation Where? Is it a federal or state case? If it's a federal case, in what circuit was it decided? Level of court? When? City of Austin v. Davis Tex.App. 3 Dist.,1985. Court of Appeals of Texas.Austin. CITY OF AUSTIN, Appellant, v. Kenneth Richard DAVIS, III, b/n/f Kenneth Richard Davis, Sr., et al., Appellees. No. 14246. June 5, 1985. Rehearing Denied June 26, 1985. Father disclaimed interest in action for wrongful death of his son and brought action against city hospital for his own mental distress and physical injuries sustained as bystander to finding of his son's body at base of airshaft.", "ocr": "# 1. WHAT IS THE BACKGROUND? ## - Citation - Where? - Is it a federal or state case? If it's a federal case, in what circuit was it decided? - Level of court? When? City of Austin v. Davis Tex.App. 3 Dist., 1985. Court of Appeals of Texas.Austin. CITY OF AUSTIN, Appellant, v. Kenneth Richard DAVIS, III, b/n/f Kenneth Richard Davis, Sr., et al., Appellees. No. 14246. June 5, 1985. Rehearing Denied June 26, 1985. Father disclaimed interest in action for wrongful death of his son and brought action against city hospital for his own mental distress and physical injuries sustained as bystander to finding of his son's body at base of airshaft.", "cer": 0.018957345971563982, "wer": 0.06481481481481481, "accuracy": 98.10426540284361, "order_agnostic_accuray": 100.0, "processing_time": 1.785742998123169}, {"video_id": "m-z-0194c270-bbfb-7dd2-aaec-62d909b97b32", "scene_start": 31.0, "Scene_end": 32.0, "image": ["https://storage.videodb.io/media/u-0e58db00-6548-4d3c-b8c1-4ddddc072787/m-z-0194c270-bbfb-7dd2-aaec-62d909b97b32/frames/frm-scn-tt1sff1-31.0-32.0-31.5/img-f2105518-494e-463b-a971-61942471bbb0.png"], "ground_truth": "1. WHAT IS THE BACKGROUND? - Citation Where? Is it a federal or state case? If it's a federal case, in what circuit was it decided? Level of court? When? City of Austin v. Davis Tex.App. 3 Dist.,1985. Court of Appeals of Texas.Austin. CITY OF AUSTIN, Appellant, v. Kenneth Richard DAVIS, III, b/n/f Kenneth Richard Davis, Sr., et al., Appellees. No. 14246. June 5, 1985. Rehearing Denied June 26, 1985. Father disclaimed interest in action for wrongful death of his son and brought action against city hospital for his own mental distress and physical injuries sustained as bystander to finding of his son's body at base of airshaft.", "ocr": "# 1. WHAT IS THE BACKGROUND? ## - Citation - Where? - Is it a federal or state case? If it's a federal case, in what circuit was it decided? - Level of court? When? City of Austin v. Davis Tex.App. 3 Dist., 1985. Court of Appeals of Texas.Austin. CITY OF AUSTIN, Appellant, v. Kenneth Richard DAVIS, III, b/n/f Kenneth Richard Davis, Sr., et al., Appellees. No. 14246. June 5, 1985. Rehearing Denied June 26, 1985. Father disclaimed interest in action for wrongful death of his son and brought action against city hospital for his own mental distress and physical injuries sustained as bystander to finding of his son's body at base of airshaft.", "cer": 0.018957345971563982, "wer": 0.06481481481481481, "accuracy": 98.10426540284361, "order_agnostic_accuray": 100.0, "processing_time": 2.081449508666992}, {"video_id": "m-z-0194c270-bbfb-7dd2-aaec-62d909b97b32", "scene_start": 32.0, "Scene_end": 33.0, "image": ["https://storage.videodb.io/media/u-0e58db00-6548-4d3c-b8c1-4ddddc072787/m-z-0194c270-bbfb-7dd2-aaec-62d909b97b32/frames/frm-scn-tt1sff1-32.0-33.0-32.5/img-35f0fd56-9c6d-4271-b5ee-4efaa985f9ab.png"], "ground_truth": "1. WHAT IS THE BACKGROUND? - Citation Where? Is it a federal or state case? If it's a federal case, in what circuit was it decided? Level of court? When? City of Austin v. Davis Tex.App. 3 Dist.,1985. Court of Appeals of Texas.Austin. CITY OF AUSTIN, Appellant, v. Kenneth Richard DAVIS, III, b/n/f Kenneth Richard Davis, Sr., et al., Appellees. No. 14246. June 5, 1985. Rehearing Denied June 26, 1985. Father disclaimed interest in action for wrongful death of his son and brought action against city hospital for his own mental distress and physical injuries sustained as bystander to finding of his son's body at base of airshaft.", "ocr": "# 1. WHAT IS THE BACKGROUND? ## - Citation - Where? - Is it a federal or state case? If it's a federal case, in what circuit was it decided? - Level of court? When? City of Austin v. Davis Tex.App. 3 Dist., 1985. Court of Appeals of Texas.Austin. CITY OF AUSTIN, Appellant, v. Kenneth Richard DAVIS, III, b/n/f Kenneth Richard Davis, Sr., et al., Appellees. No. 14246. June 5, 1985. Rehearing Denied June 26, 1985. Father disclaimed interest in action for wrongful death of his son and brought action against city hospital for his own mental distress and physical injuries sustained as bystander to finding of his son's body at base of airshaft.", "cer": 0.018957345971563982, "wer": 0.06481481481481481, "accuracy": 98.10426540284361, "order_agnostic_accuray": 100.0, "processing_time": 1.9725096225738525}, {"video_id": "m-z-0194c270-bbfb-7dd2-aaec-62d909b97b32", "scene_start": 33.0, "Scene_end": 34.0, "image": ["https://storage.videodb.io/media/u-0e58db00-6548-4d3c-b8c1-4ddddc072787/m-z-0194c270-bbfb-7dd2-aaec-62d909b97b32/frames/frm-scn-tt1sff1-33.0-34.0-33.5/img-71ebec71-6d79-47d7-968a-abfbd791409e.png"], "ground_truth": "1. WHAT IS THE BACKGROUND? - Citation Where? Is it a federal or state case? If it's a federal case, in what circuit was it decided? Level of court? When? City of Austin v. Davis Tex.App. 3 Dist.,1985. Court of Appeals of Texas.Austin. CITY OF AUSTIN, Appellant, v. Kenneth Richard DAVIS, III, b/n/f Kenneth Richard Davis, Sr., et al., Appellees. No. 14246. June 5, 1985. Rehearing Denied June 26, 1985. Father disclaimed interest in action for wrongful death of his son and brought action against city hospital for his own mental distress and physical injuries sustained as bystander to finding of his son's body at base of airshaft.", "ocr": "# 1. WHAT IS THE BACKGROUND? ## - Citation - Where? - Is it a federal or state case? If it's a federal case, in what circuit was it decided? - Level of court? ## - When? City of Austin v. Davis Tex.App. 3 Dist., 1985. Court of Appeals of Texas.Austin. CITY OF AUSTIN, Appellant, v. Kenneth Richard DAVIS, III, b/n/f Kenneth Richard Davis, Sr., et al., Appellees. No. 14246. June 5, 1985. Rehearing Denied June 26, 1985. Father disclaimed interest in action for wrongful death of his son and brought action against city hospital for his own mental distress and physical injuries sustained as bystander to finding of his son's body at base of airshaft.", "cer": 0.026856240126382307, "wer": 0.08333333333333333, "accuracy": 97.31437598736177, "order_agnostic_accuray": 100.0, "processing_time": 1.7391819953918457}, {"video_id": "m-z-0194c270-bbfb-7dd2-aaec-62d909b97b32", "scene_start": 34.0, "Scene_end": 35.0, "image": ["https://storage.videodb.io/media/u-0e58db00-6548-4d3c-b8c1-4ddddc072787/m-z-0194c270-bbfb-7dd2-aaec-62d909b97b32/frames/frm-scn-tt1sff1-34.0-35.0-34.5/img-2bfa1f3a-af69-463f-95fa-782dbf20e7d5.png"], "ground_truth": "1. WHAT IS THE BACKGROUND? - Citation Where? Is it a federal or state case? If it's a federal case, in what circuit was it decided? Level of court? When? City of Austin v. Davis Tex.App. 3 Dist.,1985. Court of Appeals of Texas.Austin. CITY OF AUSTIN, Appellant, v. Kenneth Richard DAVIS, III, b/n/f Kenneth Richard Davis, Sr., et al., Appellees. No. 14246. June 5, 1985. Rehearing Denied June 26, 1985. Father disclaimed interest in action for wrongful death of his son and brought action against city hospital for his own mental distress and physical injuries sustained as bystander to finding of his son's body at base of airshaft.", "ocr": "# 693 S.W.2d 31 City of Austin v. Davis Tex.App. 3 Dist.,1985. Court of Appeals of Texas.Austin. CITY OF AUSTIN, Appellant, v. Kenneth Richard DAVIS, III, b/n/f Kenneth Richard Davis, Sr., et al., Appellees. No. 14246. June 5, 1985. Rehearing Denied June 26, 1985. Father disclaimed interest in action for wrongful death of his son and brought action against city hospital for his own mental distress and physical injuries sustained as bystander to finding of his son's body at base of airshaft.", "cer": 0.23222748815165878, "wer": 0.2777777777777778, "accuracy": 76.77725118483411, "order_agnostic_accuray": 77.09320695102686, "processing_time": 1.713775396347046}, {"video_id": "m-z-0194c270-bbfb-7dd2-aaec-62d909b97b32", "scene_start": 35.0, "Scene_end": 36.0, "image": ["https://storage.videodb.io/media/u-0e58db00-6548-4d3c-b8c1-4ddddc072787/m-z-0194c270-bbfb-7dd2-aaec-62d909b97b32/frames/frm-scn-tt1sff1-35.0-36.0-35.5/img-eec8eedf-8844-4bc1-a523-970c540d960c.png"], "ground_truth": "693 S.W.2d 31 City of Austin v. Davis Tex.App. 3 Dist.,1985. Court of Appeals of Texas.Austin. CITY OF AUSTIN, Appellant, v. Kenneth Richard DAVIS, III, b/n/f Kenneth Richard Davis, Sr., et al., Appellees. No. 14246. June 5, 1985. Rehearing Denied June 26, 1985. Father disclaimed interest in action for wrongful death of his son and brought action against city hospital for his own mental distress and physical injuries sustained as bystander to finding of his son's body at base of airshaft.", "ocr": "# 693 S.W.2d 31 City of Austin v. Davis Tex.App. 3 Dist.,1985. Court of Appeals of Texas.Austin. CITY OF AUSTIN, Appellant, v. Kenneth Richard DAVIS, III, b/n/f Kenneth Richard Davis, Sr., et al., Appellees. No. 14246. June 5, 1985. Rehearing Denied June 26, 1985. Father disclaimed interest in action for wrongful death of his son and brought action against city hospital for his own mental distress and physical injuries sustained as bystander to finding of his son's body at base of airshaft.", "cer": 0.004056795131845842, "wer": 0.012345679012345678, "accuracy": 99.59432048681542, "order_agnostic_accuray": 100.0, "processing_time": 1.7825536727905273}, {"video_id": "m-z-0194c270-bbfb-7dd2-aaec-62d909b97b32", "scene_start": 36.0, "Scene_end": 37.0, "image": ["https://storage.videodb.io/media/u-0e58db00-6548-4d3c-b8c1-4ddddc072787/m-z-0194c270-bbfb-7dd2-aaec-62d909b97b32/frames/frm-scn-tt1sff1-36.0-37.0-36.5/img-7e0a8804-59e7-49ec-9b47-91652ce0f0d2.png"], "ground_truth": "693 S.W.2d 31 City of Austin v. Davis Tex.App. 3 Dist.,1985. Court of Appeals of Texas.Austin. CITY OF AUSTIN, Appellant, v. Kenneth Richard DAVIS, III, b/n/f Kenneth Richard Davis, Sr., et al., Appellees. No. 14246. June 5, 1985. Rehearing Denied June 26, 1985. Father disclaimed interest in action for wrongful death of his son and brought action against city hospital for his own mental distress and physical injuries sustained as bystander to finding of his son's body at base of airshaft.", "ocr": "# 693 S.W.2d 31 City of Austin v. Davis Tex.App. 3 Dist.,1985. Court of Appeals of Texas.Austin. CITY OF AUSTIN, Appellant, v. Kenneth Richard DAVIS, III, b/n/f Kenneth Richard Davis, Sr., et al., Appellees. No. 14246. June 5, 1985. Rehearing Denied June 26, 1985. Father disclaimed interest in action for wrongful death of his son and brought action against city hospital for his own mental distress and physical injuries sustained as bystander to finding of his son's body at base of airshaft.", "cer": 0.004056795131845842, "wer": 0.012345679012345678, "accuracy": 99.59432048681542, "order_agnostic_accuray": 100.0, "processing_time": 1.6213343143463135}, {"video_id": "m-z-0194c270-bbfb-7dd2-aaec-62d909b97b32", "scene_start": 37.0, "Scene_end": 38.0, "image": ["https://storage.videodb.io/media/u-0e58db00-6548-4d3c-b8c1-4ddddc072787/m-z-0194c270-bbfb-7dd2-aaec-62d909b97b32/frames/frm-scn-tt1sff1-37.0-38.0-37.5/img-c1dd8d09-3100-45cd-b701-0cf7e28ddf2a.png"], "ground_truth": "693 S.W.2d 31 City of Austin v. Davis Tex.App. 3 Dist.,1985. Court of Appeals of Texas.Austin. CITY OF AUSTIN, Appellant, v. Kenneth Richard DAVIS, III, b/n/f Kenneth Richard Davis, Sr., et al., Appellees. No. 14246. June 5, 1985. Rehearing Denied June 26, 1985. Father disclaimed interest in action for wrongful death of his son and brought action against city hospital for his own mental distress and physical injuries sustained as bystander to finding of his son's body at base of airshaft.", "ocr": "# 693 S.W.2d 31 City of Austin v. Davis Tex.App. 3 Dist.,1985. Court of Appeals of Texas.Austin. CITY OF AUSTIN, Appellant, v. Kenneth Richard DAVIS, III, b/n/f Kenneth Richard Davis, Sr., et al., Appellees. No. 14246. June 5, 1985. Rehearing Denied June 26, 1985. Father disclaimed interest in action for wrongful death of his son and brought action against city hospital for his own mental distress and physical injuries sustained as bystander to finding of his son's body at base of airshaft.", "cer": 0.004056795131845842, "wer": 0.012345679012345678, "accuracy": 99.59432048681542, "order_agnostic_accuray": 100.0, "processing_time": 1.5058691501617432}, {"video_id": "m-z-0194c270-bbfb-7dd2-aaec-62d909b97b32", "scene_start": 38.0, "Scene_end": 39.0, "image": ["https://storage.videodb.io/media/u-0e58db00-6548-4d3c-b8c1-4ddddc072787/m-z-0194c270-bbfb-7dd2-aaec-62d909b97b32/frames/frm-scn-tt1sff1-38.0-39.0-38.5/img-e2c9976d-a6e8-4db9-98ec-f71c25d4eef9.png"], "ground_truth": "693 S.W.2d 31 City of Austin v. Davis Tex.App. 3 Dist.,1985. Court of Appeals of Texas.Austin. CITY OF AUSTIN, Appellant, v. Kenneth Richard DAVIS, III, b/n/f Kenneth Richard Davis, Sr., et al., Appellees. No. 14246. June 5, 1985. Rehearing Denied June 26, 1985. Father disclaimed interest in action for wrongful death of his son and brought action against city hospital for his own mental distress and physical injuries sustained as bystander to finding of his son's body at base of airshaft.", "ocr": "# 693 S.W.2d 31 City of Austin v. Davis Tex.App. 3 Dist.,1985. Court of Appeals of Texas.Austin. CITY OF AUSTIN, Appellant, v. Kenneth Richard DAVIS, III, b/n/f Kenneth Richard Davis, Sr., et al., Appellees. No. 14246. June 5, 1985. Rehearing Denied June 26, 1985. Father disclaimed interest in action for wrongful death of his son and brought action against city hospital for his own mental distress and physical injuries sustained as bystander to finding of his son's body at base of airshaft.", "cer": 0.004056795131845842, "wer": 0.012345679012345678, "accuracy": 99.59432048681542, "order_agnostic_accuray": 100.0, "processing_time": 1.5440385341644287}, {"video_id": "m-z-0194c270-bbfb-7dd2-aaec-62d909b97b32", "scene_start": 39.0, "Scene_end": 40.0, "image": ["https://storage.videodb.io/media/u-0e58db00-6548-4d3c-b8c1-4ddddc072787/m-z-0194c270-bbfb-7dd2-aaec-62d909b97b32/frames/frm-scn-tt1sff1-39.0-40.0-39.5/img-9e18d90e-a927-4c4f-8a91-5b9a25609d72.png"], "ground_truth": "693 S.W.2d 31 City of Austin v. Davis Tex.App. 3 Dist.,1985. Court of Appeals of Texas.Austin. CITY OF AUSTIN, Appellant, v. Kenneth Richard DAVIS, III, b/n/f Kenneth Richard Davis, Sr., et al., Appellees. No. 14246. June 5, 1985. Rehearing Denied June 26, 1985. Father disclaimed interest in action for wrongful death of his son and brought action against city hospital for his own mental distress and physical injuries sustained as bystander to finding of his son's body at base of airshaft.", "ocr": "# 693 S.W.2d 31 City of Austin v. Davis Tex.App. 3 Dist.,1985. Court of Appeals of Texas.Austin. CITY OF AUSTIN, Appellant, v. Kenneth Richard DAVIS, III, b/n/f Kenneth Richard Davis, Sr., et al., Appellees. No. 14246. June 5, 1985. Rehearing Denied June 26, 1985. Father disclaimed interest in action for wrongful death of his son and brought action against city hospital for his own mental distress and physical injuries sustained as bystander to finding of his son's body at base of airshaft.", "cer": 0.004056795131845842, "wer": 0.012345679012345678, "accuracy": 99.59432048681542, "order_agnostic_accuray": 100.0, "processing_time": 1.551025152206421}, {"video_id": "m-z-0194c270-bbfb-7dd2-aaec-62d909b97b32", "scene_start": 40.0, "Scene_end": 41.0, "image": ["https://storage.videodb.io/media/u-0e58db00-6548-4d3c-b8c1-4ddddc072787/m-z-0194c270-bbfb-7dd2-aaec-62d909b97b32/frames/frm-scn-tt1sff1-40.0-41.0-40.5/img-8b1ecdcc-d9a1-477c-8dc8-e75f55a5a846.png"], "ground_truth": "693 S.W.2d 31 City of Austin v. Davis Tex.App. 3 Dist.,1985. Court of Appeals of Texas.Austin. CITY OF AUSTIN, Appellant, v. Kenneth Richard DAVIS, III, b/n/f Kenneth Richard Davis, Sr., et al., Appellees. No. 14246. June 5, 1985. Rehearing Denied June 26, 1985. Father disclaimed interest in action for wrongful death of his son and brought action against city hospital for his own mental distress and physical injuries sustained as bystander to finding of his son's body at base of airshaft.", "ocr": "# 693 S.W.2d 31 City of Austin v. Davis Tex.App. 3 Dist.,1985. Court of Appeals of Texas.Austin. CITY OF AUSTIN, Appellant, v. Kenneth Richard DAVIS, III, b/n/f Kenneth Richard Davis, Sr., et al., Appellees. No. 14246. June 5, 1985. Rehearing Denied June 26, 1985. Father disclaimed interest in action for wrongful death of his son and brought action against city hospital for his own mental distress and physical injuries sustained as bystander to finding of his son's body at base of airshaft.", "cer": 0.004056795131845842, "wer": 0.012345679012345678, "accuracy": 99.59432048681542, "order_agnostic_accuray": 100.0, "processing_time": 1.6244072914123535}, {"video_id": "m-z-0194c270-bbfb-7dd2-aaec-62d909b97b32", "scene_start": 41.0, "Scene_end": 42.0, "image": ["https://storage.videodb.io/media/u-0e58db00-6548-4d3c-b8c1-4ddddc072787/m-z-0194c270-bbfb-7dd2-aaec-62d909b97b32/frames/frm-scn-tt1sff1-41.0-42.0-41.5/img-ae5e6763-3a99-426d-8055-763282a7c9ee.png"], "ground_truth": "693 S.W.2d 31 City of Austin v. Davis Tex.App. 3 Dist.,1985. Court of Appeals of Texas.Austin. CITY OF AUSTIN, Appellant, v. Kenneth Richard DAVIS, III, b/n/f Kenneth Richard Davis, Sr., et al., Appellees. No. 14246. June 5, 1985. Rehearing Denied June 26, 1985. Father disclaimed interest in action for wrongful death of his son and brought action against city hospital for his own mental distress and physical injuries sustained as bystander to finding of his son's body at base of airshaft.", "ocr": "# 693 S.W.2d 31 City of Austin v. Davis Tex.App. 3 Dist.,1985. Court of Appeals of Texas.Austin. CITY OF AUSTIN, Appellant, v. Kenneth Richard DAVIS, III, b/n/f Kenneth Richard Davis, Sr., et al., Appellees. No. 14246. June 5, 1985. Rehearing Denied June 26, 1985. Father disclaimed interest in action for wrongful death of his son and brought action against city hospital for his own mental distress and physical injuries sustained as bystander to finding of his son's body at base of airshaft.", "cer": 0.004056795131845842, "wer": 0.012345679012345678, "accuracy": 99.59432048681542, "order_agnostic_accuray": 100.0, "processing_time": 0.5579879283905029}, {"video_id": "m-z-0194c270-bbfb-7dd2-aaec-62d909b97b32", "scene_start": 42.0, "Scene_end": 43.0, "image": ["https://storage.videodb.io/media/u-0e58db00-6548-4d3c-b8c1-4ddddc072787/m-z-0194c270-bbfb-7dd2-aaec-62d909b97b32/frames/frm-scn-tt1sff1-42.0-43.0-42.5/img-4090d7bc-6e05-4434-a4cd-11080cf2c27b.png"], "ground_truth": "693 S.W.2d 31 City of Austin v. Davis Tex.App. 3 Dist.,1985. Court of Appeals of Texas.Austin. CITY OF AUSTIN, Appellant, v. Kenneth Richard DAVIS, III, b/n/f Kenneth Richard Davis, Sr., et al., Appellees. No. 14246. June 5, 1985. Rehearing Denied June 26, 1985. Father disclaimed interest in action for wrongful death of his son and brought action against city hospital for his own mental distress and physical injuries sustained as bystander to finding of his son's body at base of airshaft.", "ocr": "# 693 S.W.2d 31 City of Austin v. Davis Tex.App. 3 Dist.,1985. Court of Appeals of Texas.Austin. CITY OF AUSTIN, Appellant, v. Kenneth Richard DAVIS, III, b/n/f Kenneth Richard Davis, Sr., et al., Appellees. No. 14246. June 5, 1985. Rehearing Denied June 26, 1985. Father disclaimed interest in action for wrongful death of his son and brought action against city hospital for his own mental distress and physical injuries sustained as bystander to finding of his son's body at base of airshaft.", "cer": 0.004056795131845842, "wer": 0.012345679012345678, "accuracy": 99.59432048681542, "order_agnostic_accuray": 100.0, "processing_time": 0.657545804977417}, {"video_id": "m-z-0194c270-bbfb-7dd2-aaec-62d909b97b32", "scene_start": 43.0, "Scene_end": 44.0, "image": ["https://storage.videodb.io/media/u-0e58db00-6548-4d3c-b8c1-4ddddc072787/m-z-0194c270-bbfb-7dd2-aaec-62d909b97b32/frames/frm-scn-tt1sff1-43.0-44.0-43.5/img-d5d77198-649d-4689-8306-3600a7d8143b.png"], "ground_truth": "693 S.W.2d 31 City of Austin v. Davis Tex.App. 3 Dist.,1985. Court of Appeals of Texas.Austin. CITY OF AUSTIN, Appellant, v. Kenneth Richard DAVIS, III, b/n/f Kenneth Richard Davis, Sr., et al., Appellees. No. 14246. June 5, 1985. Rehearing Denied June 26, 1985. Father disclaimed interest in action for wrongful death of his son and brought action against city hospital for his own mental distress and physical injuries sustained as bystander to finding of his son's body at base of airshaft.", "ocr": "# 693 S.W.2d 31 City of Austin v. Davis Tex.App. 3 Dist.,1985. Court of Appeals of Texas.Austin. CITY OF AUSTIN, Appellant, v. Kenneth Richard DAVIS, III, b/n/f Kenneth Richard Davis, Sr., et al., Appellees. No. 14246. June 5, 1985. Rehearing Denied June 26, 1985. Father disclaimed interest in action for wrongful death of his son and brought action against city hospital for his own mental distress and physical injuries sustained as bystander to finding of his son's body at base of airshaft.", "cer": 0.004056795131845842, "wer": 0.012345679012345678, "accuracy": 99.59432048681542, "order_agnostic_accuray": 100.0, "processing_time": 1.559248924255371}, {"video_id": "m-z-0194c270-bbfb-7dd2-aaec-62d909b97b32", "scene_start": 44.0, "Scene_end": 45.0, "image": ["https://storage.videodb.io/media/u-0e58db00-6548-4d3c-b8c1-4ddddc072787/m-z-0194c270-bbfb-7dd2-aaec-62d909b97b32/frames/frm-scn-tt1sff1-44.0-45.0-44.5/img-8a6c6344-f124-43e2-a302-35708f6fb446.png"], "ground_truth": "693 S.W.2d 31 City of Austin v. Davis Tex.App. 3 Dist.,1985. Court of Appeals of Texas.Austin. CITY OF AUSTIN, Appellant, v. Kenneth Richard DAVIS, III, b/n/f Kenneth Richard Davis, Sr., et al., Appellees. No. 14246. June 5, 1985. Rehearing Denied June 26, 1985. Father disclaimed interest in action for wrongful death of his son and brought action against city hospital for his own mental distress and physical injuries sustained as bystander to finding of his son's body at base of airshaft.", "ocr": "# 693 S.W.2d 31 City of Austin v. Davis Tex.App. 3 Dist.,1985. Court of Appeals of Texas.Austin. CITY OF AUSTIN, Appellant, v. Kenneth Richard DAVIS, III, b/n/f Kenneth Richard Davis, Sr., et al., Appellees. No. 14246. June 5, 1985. Rehearing Denied June 26, 1985. Father disclaimed interest in action for wrongful death of his son and brought action against city hospital for his own mental distress and physical injuries sustained as bystander to finding of his son's body at base of airshaft.", "cer": 0.004056795131845842, "wer": 0.012345679012345678, "accuracy": 99.59432048681542, "order_agnostic_accuray": 100.0, "processing_time": 1.5209109783172607}, {"video_id": "m-z-0194c270-bbfb-7dd2-aaec-62d909b97b32", "scene_start": 45.0, "Scene_end": 46.0, "image": ["https://storage.videodb.io/media/u-0e58db00-6548-4d3c-b8c1-4ddddc072787/m-z-0194c270-bbfb-7dd2-aaec-62d909b97b32/frames/frm-scn-tt1sff1-45.0-46.0-45.5/img-5de84b17-3419-40dc-87b2-fde80d68266e.png"], "ground_truth": "693 S.W.2d 31 City of Austin v. Davis Tex.App. 3 Dist.,1985. Court of Appeals of Texas.Austin. CITY OF AUSTIN, Appellant, v. Kenneth Richard DAVIS, III, b/n/f Kenneth Richard Davis, Sr., et al., Appellees. No. 14246. June 5, 1985. Rehearing Denied June 26, 1985. Father disclaimed interest in action for wrongful death of his son and brought action against city hospital for his own mental distress and physical injuries sustained as bystander to finding of his son's body at base of airshaft.", "ocr": "# 693 S.W.2d 31 City of Austin v. Davis Tex.App. 3 Dist.,1985. Court of Appeals of Texas.Austin. CITY OF AUSTIN, Appellant, v. Kenneth Richard DAVIS, III, b/n/f Kenneth Richard Davis, Sr., et al., Appellees. No. 14246. June 5, 1985. Rehearing Denied June 26, 1985. Father disclaimed interest in action for wrongful death of his son and brought action against city hospital for his own mental distress and physical injuries sustained as bystander to finding of his son's body at base of airshaft.", "cer": 0.004056795131845842, "wer": 0.012345679012345678, "accuracy": 99.59432048681542, "order_agnostic_accuray": 100.0, "processing_time": 0.5597293376922607}, {"video_id": "m-z-0194c270-bbfb-7dd2-aaec-62d909b97b32", "scene_start": 46.0, "Scene_end": 47.0, "image": ["https://storage.videodb.io/media/u-0e58db00-6548-4d3c-b8c1-4ddddc072787/m-z-0194c270-bbfb-7dd2-aaec-62d909b97b32/frames/frm-scn-tt1sff1-46.0-47.0-46.5/img-a8253693-c9a8-49fb-a3b2-cb49c00544f1.png"], "ground_truth": "693 S.W.2d 31 City of Austin v. Davis Tex.App. 3 Dist.,1985. Court of Appeals of Texas.Austin. CITY OF AUSTIN, Appellant, v. Kenneth Richard DAVIS, III, b/n/f Kenneth Richard Davis, Sr., et al., Appellees. No. 14246. June 5, 1985. Rehearing Denied June 26, 1985. Father disclaimed interest in action for wrongful death of his son and brought action against city hospital for his own mental distress and physical injuries sustained as bystander to finding of his son's body at base of airshaft.", "ocr": "# 693 S.W.2d 31 City of Austin v. Davis Tex.App. 3 Dist.,1985. Court of Appeals of Texas.Austin. CITY OF AUSTIN, Appellant, v. Kenneth Richard DAVIS, III, b/n/f Kenneth Richard Davis, Sr., et al., Appellees. No. 14246. June 5, 1985. Rehearing Denied June 26, 1985. Father disclaimed interest in action for wrongful death of his son and brought action against city hospital for his own mental distress and physical injuries sustained as bystander to finding of his son's body at base of airshaft.", "cer": 0.004056795131845842, "wer": 0.012345679012345678, "accuracy": 99.59432048681542, "order_agnostic_accuray": 100.0, "processing_time": 1.58986496925354}, {"video_id": "m-z-0194c270-bbfb-7dd2-aaec-62d909b97b32", "scene_start": 47.0, "Scene_end": 48.0, "image": ["https://storage.videodb.io/media/u-0e58db00-6548-4d3c-b8c1-4ddddc072787/m-z-0194c270-bbfb-7dd2-aaec-62d909b97b32/frames/frm-scn-tt1sff1-47.0-48.0-47.5/img-2acc5590-ddfa-4815-83c1-1fa042f99514.png"], "ground_truth": "", "ocr": "", "cer": 1.0, "wer": 1.0, "accuracy": 0.0, "order_agnostic_accuray": 0.0, "processing_time": 0.6820037364959717}, {"video_id": "m-z-0194c270-bbfb-7dd2-aaec-62d909b97b32", "scene_start": 48.0, "Scene_end": 48.8, "image": ["https://storage.videodb.io/media/u-0e58db00-6548-4d3c-b8c1-4ddddc072787/m-z-0194c270-bbfb-7dd2-aaec-62d909b97b32/frames/frm-scn-tt1sff1-48.0-48.8-48.4/img-03705e53-773d-4ceb-9d7e-ddb223a3f1b5.png"], "ground_truth": "", "ocr": "", "cer": 1.0, "wer": 1.0, "accuracy": 0.0, "order_agnostic_accuray": 0.0, "processing_time": 0.5334100723266602}]